primo/javi_primo.py
primo/primo.py
javi_primo-0.5.dist-info/LICENSE.txt
javi_primo-0.5.dist-info/METADATA
javi_primo-0.5.dist-info/WHEEL
javi_primo-0.5.dist-info/top_level.txt
javi_primo-0.5.dist-info/RECORD
